python_rate_limiter/__init__.py
python_rate_limiter/core.py
python_rate_limiter/fastapi_integration.py
python_rate_limiter/flask_integration.py
python_rate_limiter-1.0.0.dist-info/METADATA
python_rate_limiter-1.0.0.dist-info/WHEEL
python_rate_limiter-1.0.0.dist-info/top_level.txt
python_rate_limiter-1.0.0.dist-info/RECORD
